
const size_t POP_TOP = 1;
const size_t ROT_TWO = 2;
const size_t ROT_THREE = 3;
const size_t DUP_TOP = 4;
const size_t DUP_TOP_TWO = 5;
const size_t ROT_FOUR = 6;
const size_t NOP = 9;
const size_t UNARY_POSITIVE = 10;
const size_t UNARY_NEGATIVE = 11;
const size_t UNARY_NOT = 12;
const size_t UNARY_INVERT = 15;
const size_t BINARY_MATRIX_MULTIPLY = 16;
const size_t INPLACE_MATRIX_MULTIPLY = 17;
const size_t BINARY_POWER = 19;
const size_t BINARY_MULTIPLY = 20;
const size_t BINARY_MODULO = 22;
const size_t BINARY_ADD = 23;
const size_t BINARY_SUBTRACT = 24;
const size_t BINARY_SUBSCR = 25;
const size_t BINARY_FLOOR_DIVIDE = 26;
const size_t BINARY_TRUE_DIVIDE = 27;
const size_t INPLACE_FLOOR_DIVIDE = 28;
const size_t INPLACE_TRUE_DIVIDE = 29;
const size_t RERAISE = 48;
const size_t WITH_EXCEPT_START = 49;
const size_t GET_AITER = 50;
const size_t GET_ANEXT = 51;
const size_t BEFORE_ASYNC_WITH = 52;
const size_t END_ASYNC_FOR = 54;
const size_t INPLACE_ADD = 55;
const size_t INPLACE_SUBTRACT = 56;
const size_t INPLACE_MULTIPLY = 57;
const size_t INPLACE_MODULO = 59;
const size_t STORE_SUBSCR = 60;
const size_t DELETE_SUBSCR = 61;
const size_t BINARY_LSHIFT = 62;
const size_t BINARY_RSHIFT = 63;
const size_t BINARY_AND = 64;
const size_t BINARY_XOR = 65;
const size_t BINARY_OR = 66;
const size_t INPLACE_POWER = 67;
const size_t GET_ITER = 68;
const size_t GET_YIELD_FROM_ITER = 69;
const size_t PRINT_EXPR = 70;
const size_t LOAD_BUILD_CLASS = 71;
const size_t YIELD_FROM = 72;
const size_t GET_AWAITABLE = 73;
const size_t LOAD_ASSERTION_ERROR = 74;
const size_t INPLACE_LSHIFT = 75;
const size_t INPLACE_RSHIFT = 76;
const size_t INPLACE_AND = 77;
const size_t INPLACE_XOR = 78;
const size_t INPLACE_OR = 79;
const size_t LIST_TO_TUPLE = 82;
const size_t RETURN_VALUE = 83;
const size_t IMPORT_STAR = 84;
const size_t SETUP_ANNOTATIONS = 85;
const size_t YIELD_VALUE = 86;
const size_t POP_BLOCK = 87;
const size_t POP_EXCEPT = 89;
const size_t STORE_NAME = 90;
const size_t DELETE_NAME = 91;
const size_t UNPACK_SEQUENCE = 92;
const size_t FOR_ITER = 93;
const size_t UNPACK_EX = 94;
const size_t STORE_ATTR = 95;
const size_t DELETE_ATTR = 96;
const size_t STORE_GLOBAL = 97;
const size_t DELETE_GLOBAL = 98;
const size_t LOAD_CONST = 100;
const size_t LOAD_NAME = 101;
const size_t BUILD_TUPLE = 102;
const size_t BUILD_LIST = 103;
const size_t BUILD_SET = 104;
const size_t BUILD_MAP = 105;
const size_t LOAD_ATTR = 106;
const size_t COMPARE_OP = 107;
const size_t IMPORT_NAME = 108;
const size_t IMPORT_FROM = 109;
const size_t JUMP_FORWARD = 110;
const size_t JUMP_IF_FALSE_OR_POP = 111;
const size_t JUMP_IF_TRUE_OR_POP = 112;
const size_t JUMP_ABSOLUTE = 113;
const size_t POP_JUMP_IF_FALSE = 114;
const size_t POP_JUMP_IF_TRUE = 115;
const size_t LOAD_GLOBAL = 116;
const size_t IS_OP = 117;
const size_t CONTAINS_OP = 118;
const size_t JUMP_IF_NOT_EXC_MATCH = 121;
const size_t SETUP_FINALLY = 122;
const size_t LOAD_FAST = 124;
const size_t STORE_FAST = 125;
const size_t DELETE_FAST = 126;
const size_t RAISE_VARARGS = 130;
const size_t CALL_FUNCTION = 131;
const size_t MAKE_FUNCTION = 132;
const size_t BUILD_SLICE = 133;
const size_t LOAD_CLOSURE = 135;
const size_t LOAD_DEREF = 136;
const size_t STORE_DEREF = 137;
const size_t DELETE_DEREF = 138;
const size_t CALL_FUNCTION_KW = 141;
const size_t CALL_FUNCTION_EX = 142;
const size_t SETUP_WITH = 143;
const size_t LIST_APPEND = 145;
const size_t SET_ADD = 146;
const size_t MAP_ADD = 147;
const size_t LOAD_CLASSDEREF = 148;
const size_t EXTENDED_ARG = 144;
const size_t SETUP_ASYNC_WITH = 154;
const size_t FORMAT_VALUE = 155;
const size_t BUILD_CONST_KEY_MAP = 156;
const size_t BUILD_STRING = 157;
const size_t LOAD_METHOD = 160;
const size_t CALL_METHOD = 161;
const size_t LIST_EXTEND = 162;
const size_t SET_UPDATE = 163;
const size_t DICT_MERGE = 164;
const size_t DICT_UPDATE = 165;

const size_t ERROR_CODE = 256;
const size_t RANDOM_UNIFORM = 257;
const size_t RANDOM_NORMAL = 258;
const size_t RANGE = 259;
const size_t NO_AXIS = 260;
const size_t NUMPY_ARRAY = 261;
const size_t STRING = 262;
const size_t NUMBER = 263;
const size_t SEQUENCE = 264;
const size_t SLICE = 265;
const size_t KARRAY = 266;
const size_t KIPR_MODULE = 267;
const size_t MODULE = 268;
const size_t RELU_FUNCTION = 269;
const size_t SOFTMAX_FUNCTION = 270;
